CHANGES.rst
LICENSE
MANIFEST.in
README.rst
setup.py
uflash.py
uflash.egg-info/PKG-INFO
uflash.egg-info/SOURCES.txt
uflash.egg-info/dependency_links.txt
uflash.egg-info/entry_points.txt
uflash.egg-info/top_level.txt