Metadata-Version: 1.1
Name: uflash
Version: 1.0.0b7
Summary: A module and utility to flash Python onto the BBC micro:bit.
Home-page: https://github.com/ntoll/uflash
Author: Nicholas H.Tollervey
Author-email: ntoll@ntoll.org
License: MIT
Platform: UNKNOWN
Classifier: Development Status :: 4 - Beta
Classifier: Environment :: Console
Classifier: Intended Audience :: Developers
Classifier: Intended Audience :: Education
Classifier: License :: OSI Approved :: MIT License
Classifier: Operating System :: POSIX
Classifier: Operating System :: Microsoft :: Windows
Classifier: Programming Language :: Python :: 2.7
Classifier: Programming Language :: Python :: 3.3
Classifier: Topic :: Education
Classifier: Topic :: Software Development :: Embedded Systems
